{
    "id": "opt_20250731_150728",
    "date": "20250731_150728",
    "best_params": {
        "d_model": 256,
        "nhead": 2,
        "num_layers": 1,
        "lr": 0.0003222898803337917,
        "weight_decay": 1.306844524367363e-07,
        "dropout": 0.05,
        "accumulate_grad_batches": 1
    },
    "metrics": {
        "val_loss": 0.003965313097818152,
        "best_trial": 15
    },
    "trials": [
        {
            "number": 0,
            "value": 0.26218373843413945,
            "d_model": 64,
            "nhead": 4,
            "num_layers": 2,
            "lr": 1.0869465244078421e-05,
            "weight_decay": 4.316538908443051e-08,
            "dropout": 0.05,
            "accumulate_grad_batches": 1
        },
        {
            "number": 1,
            "value": 0.014680048656266402,
            "d_model": 64,
            "nhead": 1,
            "num_layers": 3,
            "lr": 0.0009714479757013238,
            "weight_decay": 6.379989555090145e-06,
            "dropout": 0.05,
            "accumulate_grad_batches": 1
        },
        {
            "number": 2,
            "value": 0.0584549996727968,
            "d_model": 128,
            "nhead": 4,
            "num_layers": 1,
            "lr": 5.3751255003384234e-05,
            "weight_decay": 6.385777674303344e-07,
            "dropout": 0.05,
            "accumulate_grad_batches": 1
        },
        {
            "number": 3,
            "value": 0.029202864998403716,
            "d_model": 128,
            "nhead": 4,
            "num_layers": 4,
            "lr": 0.0001587250797492607,
            "weight_decay": 2.7976295607535914e-06,
            "dropout": 0.05,
            "accumulate_grad_batches": 1
        },
        {
            "number": 4,
            "value": 0.22097651257782297,
            "d_model": 64,
            "nhead": 4,
            "num_layers": 4,
            "lr": 3.010990191389401e-05,
            "weight_decay": 7.4541526424319644e-06,
            "dropout": 0.05,
            "accumulate_grad_batches": 1
        },
        {
            "number": 5,
            "value": 0.01054275589173331,
            "d_model": 256,
            "nhead": 4,
            "num_layers": 1,
            "lr": 0.0005203261626841281,
            "weight_decay": 3.246952440723867e-06,
            "dropout": 0.05,
            "accumulate_grad_batches": 1
        },
        {
            "number": 6,
            "value": 0.0836976518142311,
            "d_model": 256,
            "nhead": 2,
            "num_layers": 3,
            "lr": 1.1659107636979436e-05,
            "weight_decay": 6.255791801081158e-05,
            "dropout": 0.05,
            "accumulate_grad_batches": 1
        },
        {
            "number": 7,
            "value": 0.03464476183495101,
            "d_model": 256,
            "nhead": 2,
            "num_layers": 3,
            "lr": 0.0005120837251197617,
            "weight_decay": 8.055631718552791e-07,
            "dropout": 0.05,
            "accumulate_grad_batches": 1
        },
        {
            "number": 8,
            "value": 0.18068045536603997,
            "d_model": 128,
            "nhead": 1,
            "num_layers": 3,
            "lr": 1.3481443813375817e-05,
            "weight_decay": 2.9614993898497474e-06,
            "dropout": 0.05,
            "accumulate_grad_batches": 1
        },
        {
            "number": 9,
            "value": 0.1656232480343212,
            "d_model": 64,
            "nhead": 1,
            "num_layers": 4,
            "lr": 3.3006916525737624e-05,
            "weight_decay": 4.6047553842033054e-07,
            "dropout": 0.05,
            "accumulate_grad_batches": 1
        },
        {
            "number": 10,
            "value": 0.006295457449810141,
            "d_model": 256,
            "nhead": 4,
            "num_layers": 1,
            "lr": 0.00022106745949960831,
            "weight_decay": 4.775139558742637e-08,
            "dropout": 0.05,
            "accumulate_grad_batches": 1
        },
        {
            "number": 11,
            "value": 0.0042151799151564345,
            "d_model": 256,
            "nhead": 4,
            "num_layers": 1,
            "lr": 0.0003024015877584594,
            "weight_decay": 1.4022129210573272e-08,
            "dropout": 0.05,
            "accumulate_grad_batches": 1
        },
        {
            "number": 12,
            "value": 0.00956802539226106,
            "d_model": 256,
            "nhead": 4,
            "num_layers": 1,
            "lr": 0.000167588811158109,
            "weight_decay": 1.5989637139045577e-08,
            "dropout": 0.05,
            "accumulate_grad_batches": 1
        },
        {
            "number": 13,
            "value": 0.010589662829742712,
            "d_model": 256,
            "nhead": 4,
            "num_layers": 2,
            "lr": 0.00025878351249220563,
            "weight_decay": 9.624420944467131e-08,
            "dropout": 0.05,
            "accumulate_grad_batches": 1
        },
        {
            "number": 14,
            "value": 0.006747257142492077,
            "d_model": 256,
            "nhead": 4,
            "num_layers": 2,
            "lr": 8.952794800480439e-05,
            "weight_decay": 1.2226220238943154e-08,
            "dropout": 0.05,
            "accumulate_grad_batches": 1
        },
        {
            "number": 15,
            "value": 0.003965313097818152,
            "d_model": 256,
            "nhead": 2,
            "num_layers": 1,
            "lr": 0.0003222898803337917,
            "weight_decay": 1.306844524367363e-07,
            "dropout": 0.05,
            "accumulate_grad_batches": 1
        },
        {
            "number": 16,
            "value": 0.012887876987566842,
            "d_model": 256,
            "nhead": 2,
            "num_layers": 2,
            "lr": 0.000401828986135866,
            "weight_decay": 1.9355475407825742e-07,
            "dropout": 0.05,
            "accumulate_grad_batches": 1
        },
        {
            "number": 17,
            "value": 0.04789047989556018,
            "d_model": 256,
            "nhead": 2,
            "num_layers": 1,
            "lr": 0.0008417106319889721,
            "weight_decay": 1.5107868610693928e-07,
            "dropout": 0.05,
            "accumulate_grad_batches": 1
        },
        {
            "number": 18,
            "value": 0.007785251792109407,
            "d_model": 256,
            "nhead": 2,
            "num_layers": 1,
            "lr": 9.159074206323834e-05,
            "weight_decay": 2.6507678889358265e-08,
            "dropout": 0.05,
            "accumulate_grad_batches": 1
        },
        {
            "number": 19,
            "value": 0.020165796309490416,
            "d_model": 128,
            "nhead": 2,
            "num_layers": 2,
            "lr": 0.00034718349497142966,
            "weight_decay": 2.58907906845047e-07,
            "dropout": 0.05,
            "accumulate_grad_batches": 1
        },
        {
            "number": 20,
            "value": 0.008007206919822185,
            "d_model": 256,
            "nhead": 2,
            "num_layers": 1,
            "lr": 0.00013979746114991975,
            "weight_decay": 6.418031169424501e-08,
            "dropout": 0.05,
            "accumulate_grad_batches": 1
        },
        {
            "number": 21,
            "value": 0.006213131326469867,
            "d_model": 256,
            "nhead": 4,
            "num_layers": 1,
            "lr": 0.00021909743112377922,
            "weight_decay": 4.446093382260225e-08,
            "dropout": 0.05,
            "accumulate_grad_batches": 1
        },
        {
            "number": 22,
            "value": 0.01939784683396711,
            "d_model": 256,
            "nhead": 4,
            "num_layers": 1,
            "lr": 0.000307171117826148,
            "weight_decay": 1.0163892357035979e-08,
            "dropout": 0.05,
            "accumulate_grad_batches": 1
        },
        {
            "number": 23,
            "value": 0.02156946632791968,
            "d_model": 256,
            "nhead": 1,
            "num_layers": 2,
            "lr": 0.000567081635234461,
            "weight_decay": 2.6871509451597045e-08,
            "dropout": 0.05,
            "accumulate_grad_batches": 1
        },
        {
            "number": 24,
            "value": 0.008124983965364449,
            "d_model": 256,
            "nhead": 4,
            "num_layers": 1,
            "lr": 0.00020979605788263474,
            "weight_decay": 1.298326964469841e-07,
            "dropout": 0.05,
            "accumulate_grad_batches": 1
        },
        {
            "number": 25,
            "value": 0.009098447229274931,
            "d_model": 256,
            "nhead": 2,
            "num_layers": 1,
            "lr": 0.00012145721423871963,
            "weight_decay": 2.5982148690165038e-08,
            "dropout": 0.05,
            "accumulate_grad_batches": 1
        },
        {
            "number": 26,
            "value": 0.01813193377764786,
            "d_model": 256,
            "nhead": 4,
            "num_layers": 2,
            "lr": 7.199465990156555e-05,
            "weight_decay": 7.51857311615153e-08,
            "dropout": 0.05,
            "accumulate_grad_batches": 1
        },
        {
            "number": 27,
            "value": 0.03921777752282865,
            "d_model": 256,
            "nhead": 1,
            "num_layers": 1,
            "lr": 0.0006103943615127122,
            "weight_decay": 3.1125294415373354e-07,
            "dropout": 0.05,
            "accumulate_grad_batches": 1
        },
        {
            "number": 28,
            "value": 0.007898366582059465,
            "d_model": 128,
            "nhead": 4,
            "num_layers": 2,
            "lr": 0.00037344645187131314,
            "weight_decay": 2.1479875038853217e-08,
            "dropout": 0.05,
            "accumulate_grad_batches": 1
        },
        {
            "number": 29,
            "value": 0.02678933779380339,
            "d_model": 64,
            "nhead": 2,
            "num_layers": 1,
            "lr": 0.00020929884504541804,
            "weight_decay": 3.589973918345502e-08,
            "dropout": 0.05,
            "accumulate_grad_batches": 1
        },
        {
            "number": 30,
            "value": 0.011908757897532162,
            "d_model": 64,
            "nhead": 4,
            "num_layers": 2,
            "lr": 0.0007426708718064625,
            "weight_decay": 4.883313865918971e-08,
            "dropout": 0.05,
            "accumulate_grad_batches": 1
        },
        {
            "number": 31,
            "value": 0.017189841751721415,
            "d_model": 256,
            "nhead": 4,
            "num_layers": 1,
            "lr": 0.00023286856397244094,
            "weight_decay": 4.988223111606371e-08,
            "dropout": 0.05,
            "accumulate_grad_batches": 1
        },
        {
            "number": 32,
            "value": 0.009638227905858965,
            "d_model": 256,
            "nhead": 4,
            "num_layers": 1,
            "lr": 0.00027130788147676423,
            "weight_decay": 9.356453385185111e-08,
            "dropout": 0.05,
            "accumulate_grad_batches": 1
        },
        {
            "number": 33,
            "value": 0.009410373756990713,
            "d_model": 256,
            "nhead": 4,
            "num_layers": 1,
            "lr": 0.0004261555459923398,
            "weight_decay": 3.931914681172871e-08,
            "dropout": 0.05,
            "accumulate_grad_batches": 1
        },
        {
            "number": 34,
            "value": 0.01133432351600598,
            "d_model": 256,
            "nhead": 4,
            "num_layers": 1,
            "lr": 0.00018374263881182197,
            "weight_decay": 1.722350767005462e-08,
            "dropout": 0.05,
            "accumulate_grad_batches": 1
        },
        {
            "number": 35,
            "value": 0.018562004030065832,
            "d_model": 128,
            "nhead": 4,
            "num_layers": 1,
            "lr": 0.0001204694529301449,
            "weight_decay": 4.0160680999232453e-07,
            "dropout": 0.05,
            "accumulate_grad_batches": 1
        },
        {
            "number": 36,
            "value": 0.14791324909995585,
            "d_model": 64,
            "nhead": 4,
            "num_layers": 1,
            "lr": 5.6766253844075674e-05,
            "weight_decay": 1.4082454543714888e-06,
            "dropout": 0.05,
            "accumulate_grad_batches": 1
        },
        {
            "number": 37,
            "value": 0.006604943195056608,
            "d_model": 256,
            "nhead": 4,
            "num_layers": 2,
            "lr": 0.0002722097538205259,
            "weight_decay": 2.9083783315548404e-05,
            "dropout": 0.05,
            "accumulate_grad_batches": 1
        },
        {
            "number": 38,
            "value": 0.01882587970398805,
            "d_model": 256,
            "nhead": 1,
            "num_layers": 1,
            "lr": 0.0001443897670418484,
            "weight_decay": 1.0210752528488544e-08,
            "dropout": 0.05,
            "accumulate_grad_batches": 1
        },
        {
            "number": 39,
            "value": 0.034739652936182475,
            "d_model": 256,
            "nhead": 4,
            "num_layers": 1,
            "lr": 0.0004404503967169772,
            "weight_decay": 1.089718543218251e-07,
            "dropout": 0.05,
            "accumulate_grad_batches": 1
        },
        {
            "number": 40,
            "value": 0.015595035874010885,
            "d_model": 128,
            "nhead": 2,
            "num_layers": 4,
            "lr": 0.000714486926662152,
            "weight_decay": 1.179369631081046e-06,
            "dropout": 0.05,
            "accumulate_grad_batches": 1
        },
        {
            "number": 41,
            "value": 0.011077217264648746,
            "d_model": 256,
            "nhead": 4,
            "num_layers": 2,
            "lr": 0.00028976584860486334,
            "weight_decay": 4.8039951267662743e-05,
            "dropout": 0.05,
            "accumulate_grad_batches": 1
        },
        {
            "number": 42,
            "value": 0.02533182282315786,
            "d_model": 256,
            "nhead": 4,
            "num_layers": 3,
            "lr": 0.00019942093165320525,
            "weight_decay": 1.866044018992078e-05,
            "dropout": 0.05,
            "accumulate_grad_batches": 1
        },
        {
            "number": 43,
            "value": 0.005237081156605307,
            "d_model": 256,
            "nhead": 4,
            "num_layers": 2,
            "lr": 0.00032864952189117706,
            "weight_decay": 4.748888344519088e-06,
            "dropout": 0.05,
            "accumulate_grad_batches": 1
        },
        {
            "number": 44,
            "value": 0.007013483630383716,
            "d_model": 256,
            "nhead": 4,
            "num_layers": 1,
            "lr": 0.0003449971018412604,
            "weight_decay": 1.8795567962512625e-06,
            "dropout": 0.05,
            "accumulate_grad_batches": 1
        },
        {
            "number": 45,
            "value": 0.004605506581035168,
            "d_model": 256,
            "nhead": 4,
            "num_layers": 1,
            "lr": 0.00044184909788956187,
            "weight_decay": 6.401704923535409e-06,
            "dropout": 0.05,
            "accumulate_grad_batches": 1
        },
        {
            "number": 46,
            "value": 0.011863630415652604,
            "d_model": 64,
            "nhead": 4,
            "num_layers": 3,
            "lr": 0.0004750782534052564,
            "weight_decay": 9.157447150527247e-06,
            "dropout": 0.05,
            "accumulate_grad_batches": 1
        },
        {
            "number": 47,
            "value": 0.07085231486160089,
            "d_model": 256,
            "nhead": 1,
            "num_layers": 2,
            "lr": 1.9666956425507106e-05,
            "weight_decay": 5.9850928472862206e-06,
            "dropout": 0.05,
            "accumulate_grad_batches": 1
        },
        {
            "number": 48,
            "value": 0.006763747619355426,
            "d_model": 256,
            "nhead": 4,
            "num_layers": 1,
            "lr": 0.0005786159729750123,
            "weight_decay": 1.1250750046557577e-05,
            "dropout": 0.05,
            "accumulate_grad_batches": 1
        },
        {
            "number": 49,
            "value": 0.008706607855856419,
            "d_model": 256,
            "nhead": 2,
            "num_layers": 1,
            "lr": 0.00033512954848307697,
            "weight_decay": 4.462711787857719e-06,
            "dropout": 0.05,
            "accumulate_grad_batches": 1
        }
    ]
}